sundial/__init__.py
sundial-0.0.1.dist-info/METADATA
sundial-0.0.1.dist-info/WHEEL
sundial-0.0.1.dist-info/top_level.txt
sundial-0.0.1.dist-info/RECORD
